ioutrack-0.3.0.dist-info/METADATA
ioutrack-0.3.0.dist-info/WHEEL
ioutrack-0.3.0.dist-info/license_files/LICENSE
ioutrack/__init__.py
ioutrack/__init__.pyi
ioutrack/py.typed
ioutrack/ioutrack.cpython-37m-x86_64-linux-gnu.so
ioutrack-0.3.0.dist-info/RECORD
