Metadata-Version: 2.1
Name: ioutrack
Version: 0.3.0
Classifier: Programming Language :: Rust
Classifier: Programming Language :: Python :: Implementation :: CPython
Classifier: Programming Language :: Python :: Implementation :: PyPy
License-File: LICENSE
Summary: IOU-based tracking algorithms (SORT & Bytetrack) implemented in Rust
Author-email: Paul Klinger <klinger.paul@gmail.com>
Requires-Python: >=3.7
